{
  "code": "601899",
  "name": "紫金矿业",
  "annual": [
    {
      "year": "2014",
      "revenue": 587.61,
      "netProfit": 23.45,
      "revenueYoY": 18.06,
      "netProfitYoY": 10.34,
      "roe": 8.47,
      "grossMargin": 13.41,
      "netMargin": 4.49,
      "priceClose": 3.38
    },
    {
      "year": "2015",
      "revenue": 743.04,
      "netProfit": 16.56,
      "revenueYoY": 26.45,
      "netProfitYoY": -29.4,
      "roe": 6.01,
      "grossMargin": 8.47,
      "netMargin": 1.81,
      "priceClose": 3.52
    },
    {
      "year": "2016",
      "revenue": 788.51,
      "netProfit": 18.4,
      "revenueYoY": 6.12,
      "netProfitYoY": 11.12,
      "roe": 6.66,
      "grossMargin": 11.5,
      "netMargin": 2.14,
      "priceClose": 3.34
    },
    {
      "year": "2017",
      "revenue": 945.49,
      "netProfit": 35.08,
      "revenueYoY": 19.91,
      "netProfitYoY": 90.66,
      "roe": 11.1,
      "grossMargin": 13.94,
      "netMargin": 3.43,
      "priceClose": 4.59
    },
    {
      "year": "2018",
      "revenue": 1059.94,
      "netProfit": 40.94,
      "revenueYoY": 12.11,
      "netProfitYoY": 16.71,
      "roe": 11.7,
      "grossMargin": 12.59,
      "netMargin": 4.42,
      "priceClose": 3.34
    },
    {
      "year": "2019",
      "revenue": 1360.98,
      "netProfit": 42.84,
      "revenueYoY": 28.4,
      "netProfitYoY": 4.65,
      "roe": 11.38,
      "grossMargin": 11.4,
      "netMargin": 3.72,
      "priceClose": 4.59
    },
    {
      "year": "2020",
      "revenue": 1715.01,
      "netProfit": 65.09,
      "revenueYoY": 26.01,
      "netProfitYoY": 51.93,
      "roe": 12.19,
      "grossMargin": 11.91,
      "netMargin": 4.93,
      "priceClose": 9.29
    },
    {
      "year": "2021",
      "revenue": 2251.02,
      "netProfit": 156.73,
      "revenueYoY": 31.25,
      "netProfitYoY": 140.8,
      "roe": 23.97,
      "grossMargin": 15.44,
      "netMargin": 8.71,
      "priceClose": 9.7
    },
    {
      "year": "2022",
      "revenue": 2703.29,
      "netProfit": 200.42,
      "revenueYoY": 20.09,
      "netProfitYoY": 27.88,
      "roe": 25.29,
      "grossMargin": 15.74,
      "netMargin": 9.16,
      "priceClose": 10.0
    },
    {
      "year": "2023",
      "revenue": 2934.03,
      "netProfit": 211.19,
      "revenueYoY": 8.54,
      "netProfitYoY": 5.38,
      "roe": 21.43,
      "grossMargin": 15.81,
      "netMargin": 9.05,
      "priceClose": 12.46
    },
    {
      "year": "2024",
      "revenue": 3036.4,
      "netProfit": 320.51,
      "revenueYoY": 3.49,
      "netProfitYoY": 51.76,
      "roe": 25.89,
      "grossMargin": 20.37,
      "netMargin": 12.97,
      "priceClose": 15.12
    },
    {
      "year": "2025",
      "revenue": 3490.79,
      "netProfit": 517.77,
      "revenueYoY": 14.96,
      "netProfitYoY": 61.55,
      "roe": 33.04,
      "grossMargin": 27.73,
      "netMargin": 18.28,
      "priceClose": 34.47
    }
  ],
  "isCyclical": true,
  "cyclicality": "moderate",
  "position": "rising",
  "positionScore": 85,
  "summary": "成长属性突出的「成长型周期股」。虽然铜、金售价仍受商品周期影响，但公司盈利近 12 年几乎逐年增长——归母净利从 2014 年 23 亿一路攀升至 2025 年 518 亿（同比 +61.5%），ROE 从 8% 升至 33%、毛利率从 13% 升至 27.7%，期间仅 2015 年小幅回落。这种「穿越周期向上」的轨迹源于持续的产量增长：海外世界级铜矿（卡莫阿、Timok）与西藏巨龙逐年放量，量增对冲并放大了价格周期。当前盈利处历史绝对高位（约 85% 分位）且仍在上行，量价共振；但需注意铜金价格同时处于高位，若商品价格回落，高基数下的利润弹性会被放大向下。",
  "drivers": [
    "铜价（LME 铜）与金价（COMEX 黄金）—— 两大核心价格变量",
    "海外矿山产量爬坡（卡莫阿-卡库拉、Timok、西藏巨龙等放量节奏）",
    "新增并购与矿山投产带来的内生产量增长",
    "美元利率/避险情绪（影响金价）与全球制造业景气（影响铜价）"
  ],
  "source": "近 12 年年报（东财 F10 主要指标，cycle_fetch.py）/ 行业周期判断",
  "confidence": "medium",
  "reportPeriod": "2025-12-31",
  "generatedBy": "cursor-dev",
  "generatedAt": "2026-06-17T17:30:00+08:00"
}
