{
  "code": "601838",
  "name": "成都银行",
  "stance": "neutral",
  "summary": "银行政策整体呈「区域顺风、息差逆风」的对冲格局。一方面，LPR 持续下行与存量按揭、城投化债推进压缩资产端定价，净息差收窄是全行业（含成都银行）盈利增速放缓的核心压力；地产风险与地方政府债务化解过程对城商行资产质量构成尾部担忧。另一方面，存款利率市场化下调与负债成本管控为息差提供缓冲，成渝地区双城经济圈国家战略带来本地信贷与对公扩张的确定性红利，资本新规对资产质量优异、扩张稳健的成都银行影响可控，市值管理与高股息导向亦利好低估值高 ROE 银行。考虑到成都银行区域红利突出、资产质量行业领先，可对冲行业性息差压力，故综合判定为中性。",
  "events": [
    {
      "date": "2019起",
      "title": "LPR 改革与持续下行 + 净息差收窄",
      "impact": "negative",
      "note": "贷款定价基准下移叠加存量按揭利率调整，资产端收益率持续下行，净息差收窄压制利息收入增速，是行业与成都银行盈利放缓的核心政策性压力。"
    },
    {
      "date": "2022-2025",
      "title": "存款挂牌利率多轮下调 · 负债成本管控",
      "impact": "positive",
      "note": "监管引导存款利率市场化下行，降低银行负债成本，对低成本存款占比高的成都银行有效缓冲息差压力，部分对冲资产端降息。"
    },
    {
      "date": "2023-2024",
      "title": "地方政府债务化解（化债）",
      "impact": "neutral",
      "note": "化债置换降低城投相关资产收益率、短期扰动息差，但同时压降区域信用风险、改善资产质量预期；对城投/对公敞口较高的城商行影响双向。"
    },
    {
      "date": "2021起",
      "title": "房地产风险防控与化解",
      "impact": "negative",
      "note": "地产链信用风险与按揭需求走弱拖累行业资产质量与零售扩张；成都银行地产敞口相对可控、不良率行业最低，受冲击较小。"
    },
    {
      "date": "2020起",
      "title": "成渝地区双城经济圈国家战略",
      "impact": "positive",
      "note": "国家级区域战略推动成都及四川基建、产业与对公信贷高景气，为深耕本地的成都银行提供稀缺的区域成长红利，是最核心的政策顺风。"
    },
    {
      "date": "2024-2025",
      "title": "资本新规落地 + 市值管理 / 高股息导向",
      "impact": "positive",
      "note": "资本新规对资产质量优异、风险权重稳健的银行影响可控；国资委及监管推动市值管理与稳定分红，利好低估值、高 ROE、稳定派息的成都银行估值修复。"
    }
  ],
  "risks": [
    "净息差持续收窄是最确定的压制因素，若降息超预期将进一步压低利息收入增速。",
    "业务高度集中于成都/四川，区域经济、地产或地方信用一旦走弱将放大资产质量风险。",
    "城投化债与地方债务压力可能影响对公资产收益率与潜在不良生成。",
    "经济偏弱下零售信贷需求疲软、对公扩张放缓，可能拖累规模增速这一核心增长引擎。"
  ],
  "source": "央行/金融监管总局 LPR 与存款利率政策、地方化债与资本新规文件、成渝双城经济圈区域规划、成都银行 2024-2025 年报及业绩说明会、行业研报",
  "confidence": "medium",
  "reportPeriod": "2025-12-31",
  "generatedBy": "cursor-dev",
  "generatedAt": "2026-06-18T13:10:00+08:00"
}
